{"0":{"name":"2021 Stair IRC --2023 first edition --  Final Draft Folder.zip","size":"140064966","size_byte":"133.58 MB","path":"2021 Stair IRC --2023 first edition --  Final Draft Folder.zip","url":"https:\/\/sma-members.s3.amazonaws.com\/2021%20Stair%20IRC%20--2023%20first%20edition%20--%20%20Final%20Draft%20Folder.zip"},"1":{"name":"2021 Stair IRC --2023 first edition -- Final Draft PACKAGE.zip","size":"139310206","size_byte":"132.86 MB","path":"2021 Stair IRC --2023 first edition -- Final Draft PACKAGE.zip","url":"https:\/\/sma-members.s3.amazonaws.com\/2021%20Stair%20IRC%20--2023%20first%20edition%20--%20Final%20Draft%20PACKAGE.zip"},"2":{"name":"IBC-2003-Guards.doc","size":"281600","size_byte":"275.00 KB","path":"IBC-2003-Guards.doc","url":"https:\/\/sma-members.s3.amazonaws.com\/IBC-2003-Guards.doc"},"3":{"name":"IBC-2003-Live-Loads.doc","size":"358912","size_byte":"350.50 KB","path":"IBC-2003-Live-Loads.doc","url":"https:\/\/sma-members.s3.amazonaws.com\/IBC-2003-Live-Loads.doc"},"4":{"name":"IBC-2003-Stairs-and-Handrails.doc","size":"414720","size_byte":"405.00 KB","path":"IBC-2003-Stairs-and-Handrails.doc","url":"https:\/\/sma-members.s3.amazonaws.com\/IBC-2003-Stairs-and-Handrails.doc"},"5":{"name":"IBC-2009-Commentary-Guards.pdf","size":"2533727","size_byte":"2.42 MB","path":"IBC-2009-Commentary-Guards.pdf","url":"https:\/\/sma-members.s3.amazonaws.com\/IBC-2009-Commentary-Guards.pdf"},"6":{"name":"IBC-2009-Commentary-Handrails.pdf","size":"3527019","size_byte":"3.36 MB","path":"IBC-2009-Commentary-Handrails.pdf","url":"https:\/\/sma-members.s3.amazonaws.com\/IBC-2009-Commentary-Handrails.pdf"},"7":{"name":"IBC-2009-Commentary-Ramps.pdf","size":"4324618","size_byte":"4.12 MB","path":"IBC-2009-Commentary-Ramps.pdf","url":"https:\/\/sma-members.s3.amazonaws.com\/IBC-2009-Commentary-Ramps.pdf"},"8":{"name":"IBC-2009-Commentary-Stairways.pdf","size":"9747239","size_byte":"9.30 MB","path":"IBC-2009-Commentary-Stairways.pdf","url":"https:\/\/sma-members.s3.amazonaws.com\/IBC-2009-Commentary-Stairways.pdf"},"9":{"name":"IBC2009-Commentary-Live-Loads-and-Testing.pdf","size":"9075162","size_byte":"8.65 MB","path":"IBC2009-Commentary-Live-Loads-and-Testing.pdf","url":"https:\/\/sma-members.s3.amazonaws.com\/IBC2009-Commentary-Live-Loads-and-Testing.pdf"},"_nx_members":[{"name":"","size":"0","size_byte":"0 bytes","path":"members\/","url":"https:\/\/sma-members.s3.amazonaws.com\/members\/"}],"_nx_project":{"_nx_wp-content":{"_nx_uploads":{"_nx_2024":{"_nx_08":[{"name":"455185558_7956368297785172_295400462229906629_n-1024x813.jpg","size":"64414","size_byte":"62.90 KB","path":"project\/wp-content\/uploads\/2024\/08\/455185558_7956368297785172_295400462229906629_n-1024x813.jpg","url":"https:\/\/sma-members.s3.amazonaws.com\/project\/wp-content\/uploads\/2024\/08\/455185558_7956368297785172_295400462229906629_n-1024x813.jpg"},{"name":"455185558_7956368297785172_295400462229906629_n-150x150.jpg","size":"3559","size_byte":"3.48 KB","path":"project\/wp-content\/uploads\/2024\/08\/455185558_7956368297785172_295400462229906629_n-150x150.jpg","url":"https:\/\/sma-members.s3.amazonaws.com\/project\/wp-content\/uploads\/2024\/08\/455185558_7956368297785172_295400462229906629_n-150x150.jpg"},{"name":"455185558_7956368297785172_295400462229906629_n-300x238.jpg","size":"8384","size_byte":"8.19 KB","path":"project\/wp-content\/uploads\/2024\/08\/455185558_7956368297785172_295400462229906629_n-300x238.jpg","url":"https:\/\/sma-members.s3.amazonaws.com\/project\/wp-content\/uploads\/2024\/08\/455185558_7956368297785172_295400462229906629_n-300x238.jpg"},{"name":"455185558_7956368297785172_295400462229906629_n-768x609.jpg","size":"41892","size_byte":"40.91 KB","path":"project\/wp-content\/uploads\/2024\/08\/455185558_7956368297785172_295400462229906629_n-768x609.jpg","url":"https:\/\/sma-members.s3.amazonaws.com\/project\/wp-content\/uploads\/2024\/08\/455185558_7956368297785172_295400462229906629_n-768x609.jpg"},{"name":"455185558_7956368297785172_295400462229906629_n-850x565.jpg","size":"44402","size_byte":"43.36 KB","path":"project\/wp-content\/uploads\/2024\/08\/455185558_7956368297785172_295400462229906629_n-850x565.jpg","url":"https:\/\/sma-members.s3.amazonaws.com\/project\/wp-content\/uploads\/2024\/08\/455185558_7956368297785172_295400462229906629_n-850x565.jpg"},{"name":"455185558_7956368297785172_295400462229906629_n.jpg","size":"78310","size_byte":"76.47 KB","path":"project\/wp-content\/uploads\/2024\/08\/455185558_7956368297785172_295400462229906629_n.jpg","url":"https:\/\/sma-members.s3.amazonaws.com\/project\/wp-content\/uploads\/2024\/08\/455185558_7956368297785172_295400462229906629_n.jpg"}],"_nx_09":[{"name":"home-cleaning-150x150.jpeg","size":"4366","size_byte":"4.26 KB","path":"project\/wp-content\/uploads\/2024\/09\/home-cleaning-150x150.jpeg","url":"https:\/\/sma-members.s3.amazonaws.com\/project\/wp-content\/uploads\/2024\/09\/home-cleaning-150x150.jpeg"},{"name":"home-cleaning-300x200.jpeg","size":"8798","size_byte":"8.59 KB","path":"project\/wp-content\/uploads\/2024\/09\/home-cleaning-300x200.jpeg","url":"https:\/\/sma-members.s3.amazonaws.com\/project\/wp-content\/uploads\/2024\/09\/home-cleaning-300x200.jpeg"},{"name":"home-cleaning.jpeg","size":"30237","size_byte":"29.53 KB","path":"project\/wp-content\/uploads\/2024\/09\/home-cleaning.jpeg","url":"https:\/\/sma-members.s3.amazonaws.com\/project\/wp-content\/uploads\/2024\/09\/home-cleaning.jpeg"},{"name":"office-clening-150x150.jpeg","size":"3879","size_byte":"3.79 KB","path":"project\/wp-content\/uploads\/2024\/09\/office-clening-150x150.jpeg","url":"https:\/\/sma-members.s3.amazonaws.com\/project\/wp-content\/uploads\/2024\/09\/office-clening-150x150.jpeg"},{"name":"office-clening.jpeg","size":"7463","size_byte":"7.29 KB","path":"project\/wp-content\/uploads\/2024\/09\/office-clening.jpeg","url":"https:\/\/sma-members.s3.amazonaws.com\/project\/wp-content\/uploads\/2024\/09\/office-clening.jpeg"}]}}}}}